gecrooks_python_template/__init__.py
gecrooks_python_template/about.py
gecrooks_python_template/config.py
gecrooks_python_template/config_test.py
gecrooks_python_template-1.1.2.dist-info/LICENSE
gecrooks_python_template-1.1.2.dist-info/METADATA
gecrooks_python_template-1.1.2.dist-info/WHEEL
gecrooks_python_template-1.1.2.dist-info/top_level.txt
gecrooks_python_template-1.1.2.dist-info/zip-safe
gecrooks_python_template-1.1.2.dist-info/RECORD
